ecriture_shopify/__init__.py
ecriture_shopify/config/config_pays_tva.json
ecriture_shopify/core_ecriture_comptable.py
ecriture_shopify/create_xlsx.py
ecriture_shopify/load_and_clean.py
ecriture_shopify/main.py
ecriture_shopify/tools/__init__.py
ecriture_shopify/tools/convert_file_io.py
ecriture_shopify/tools/exceptions.py
ecriture_shopify/tools/read_config.py
ecriture_shopify-3.1.1.dist-info/LICENSE
ecriture_shopify-3.1.1.dist-info/METADATA
ecriture_shopify-3.1.1.dist-info/WHEEL
ecriture_shopify-3.1.1.dist-info/RECORD
