Metadata-Version: 2.1
Name: ecriture-shopify
Version: 3.1.1
Summary: Génération d'une écriture comptable à partir d'un extrait mensuel de Shopify.
Home-page: https://github.com/michelpado/ecriture-shopify
License: GPL-3.0-only
Author: michelpado
Author-email: michel.padovani@outlook.com
Requires-Python: >=3.9,<3.13
Classifier: License :: OSI Approved :: GNU General Public License v3 (GPLv3)
Classifier: Programming Language :: Python :: 3
Classifier: Programming Language :: Python :: 3.9
Classifier: Programming Language :: Python :: 3.10
Classifier: Programming Language :: Python :: 3.11
Classifier: Programming Language :: Python :: 3.12
Requires-Dist: XlsxWriter (>=3.1.9,<4.0.0)
Requires-Dist: loguru (>=0.7.2,<0.8.0)
Requires-Dist: numpy (>=1.26.0,<2.0.0)
Requires-Dist: openpyxl (>=3.1.2,<4.0.0)
Requires-Dist: pandas (>=2.1.2,<3.0.0)
Requires-Dist: xlrd (>=2.0.1,<3.0.0)
Project-URL: Changelog, https://github.com/michelpado/ecriture-shopify/blob/master/CHANGELOG.md
